rawg/__init__.py
rawg/api_client.py
rawg/configuration.py
rawg/exceptions.py
rawg/rest.py
rawg/api/__init__.py
rawg/api/creator_roles_api.py
rawg/api/creators_api.py
rawg/api/developers_api.py
rawg/api/games_api.py
rawg/api/genres_api.py
rawg/api/platforms_api.py
rawg/api/publishers_api.py
rawg/api/stores_api.py
rawg/api/tags_api.py
rawg/models/__init__.py
rawg/models/creator_roles_list200_response.py
rawg/models/creators_list200_response.py
rawg/models/developer.py
rawg/models/developer_single.py
rawg/models/developers_list200_response.py
rawg/models/game.py
rawg/models/game_esrb_rating.py
rawg/models/game_person_list.py
rawg/models/game_platform_metacritic.py
rawg/models/game_platforms_inner.py
rawg/models/game_platforms_inner_platform.py
rawg/models/game_platforms_inner_requirements.py
rawg/models/game_single.py
rawg/models/game_store_full.py
rawg/models/games_development_team_list200_response.py
rawg/models/games_list200_response.py
rawg/models/games_screenshots_list200_response.py
rawg/models/games_stores_list200_response.py
rawg/models/genre.py
rawg/models/genre_single.py
rawg/models/genres_list200_response.py
rawg/models/movie.py
rawg/models/parent_achievement.py
rawg/models/person.py
rawg/models/person_single.py
rawg/models/platform.py
rawg/models/platform_parent_single.py
rawg/models/platform_single.py
rawg/models/platforms_list200_response.py
rawg/models/platforms_lists_parents_list200_response.py
rawg/models/position.py
rawg/models/publisher.py
rawg/models/publisher_single.py
rawg/models/publishers_list200_response.py
rawg/models/reddit.py
rawg/models/screen_shot.py
rawg/models/store.py
rawg/models/store_single.py
rawg/models/stores_list200_response.py
rawg/models/tag.py
rawg/models/tag_single.py
rawg/models/tags_list200_response.py
rawg/models/twitch.py
rawg/models/youtube.py
rawg-1.2.0.dist-info/METADATA
rawg-1.2.0.dist-info/WHEEL
rawg-1.2.0.dist-info/top_level.txt
rawg-1.2.0.dist-info/RECORD
