Metadata-Version: 2.1
Name: rawg
Version: 1.2.0
Summary: RAWG.io API Wrapper
Home-page: https://github.com/uburuntu/rawg
Author: uburuntu
Author-email: bekbulatov.ramzan@ya.ru
License: UNKNOWN
Download-URL: https://github.com/uburuntu/rawg/archive/master.zip
Keywords: RAWG Video Games Database API,OpenAPI
Platform: UNKNOWN
Classifier: Development Status :: 3 - Alpha
Classifier: Intended Audience :: Developers
Classifier: Intended Audience :: System Administrators
Classifier: Programming Language :: Python :: 3
Requires-Dist: aiohttp (>=3.6.2)
Requires-Dist: certifi (>=14.05.14)
Requires-Dist: future
Requires-Dist: six (>=1.10)
Requires-Dist: python-dateutil (>=2.5.3)
Requires-Dist: setuptools (>=21.0.0)
Requires-Dist: urllib3 (>=1.25.3)
Provides-Extra: test
Requires-Dist: coverage (>=4.0.3) ; extra == 'test'
Requires-Dist: nose (>=1.3.7) ; extra == 'test'
Requires-Dist: pluggy (>=0.3.1) ; extra == 'test'
Requires-Dist: py (>=1.4.31) ; extra == 'test'
Requires-Dist: randomize (>=0.13) ; extra == 'test'
